docs_from_tests/__init__.py
docs_from_tests/call_hierarchy.py
docs_from_tests/instrument_call_hierarchy.py
docs_from_tests-0.0.2.dist-info/METADATA
docs_from_tests-0.0.2.dist-info/WHEEL
docs_from_tests-0.0.2.dist-info/top_level.txt
docs_from_tests-0.0.2.dist-info/RECORD
