Metadata-Version: 2.1
Name: docs-from-tests
Version: 0.0.2
Summary: Generate mermaid / markdown sequence diagrams from your tests
Home-page: https://github.com/resgroup/docs-from-tests
Author: RES
Author-email: cedd.burge@res-group.com
License: UNKNOWN
Platform: UNKNOWN
Requires-Python: >=3.7
